<?xml version="1.0" encoding="UTF-8"?>
<!DOCTYPE hibernate-mapping PUBLIC 
"-//Hibernate/Hibernate Mapping DTD//EN"
"http://www.hibernate.org/dtd/hibernate-mapping-3.0.dtd"> 

<hibernate-mapping>
    <class name="Beans.orders" table="orders">
        <id name="OrderId" type="int">
            <generator class="increment"/>
        </id>
        <property name="Table_No" type="int"/>
        <property name="CustomerId" type="int"/>
        <property name="active" type="int"/>
        <property name="chefId" type="int"/>
        <property name="BillAmount" type="float"/>
        <property name="TotalItemQty" type="int"/>
    </class>
</hibernate-mapping>
